Metadata-Version: 2.1
Name: teste-de-funcionalidade-camera101
Version: 1.0
Summary: apenas para teste
Author: GuilhermeCH
Author-email: guilherme.santos.ch482@gmail.com
License-File: licence.txt
